LICENSE
area_unit_conversion/__init__.py
area_unit_conversion/area_unit_conversion.py
area_unit_conversion-1.0.dist-info/entry_points.txt
area_unit_conversion-1.0.dist-info/LICENSE
area_unit_conversion-1.0.dist-info/WHEEL
area_unit_conversion-1.0.dist-info/METADATA
area_unit_conversion-1.0.dist-info/RECORD
